{"cameraMode":{"drawMode":0,"name":"Shaded","section":"Shading Mode"},"sceneLighting":true,"audioPlay":false,"sceneViewState":{"m_AlwaysRefresh":false,"showFog":true,"showSkybox":true,"showFlares":true,"showImageEffects":true,"showParticleSystems":true,"showVisualEffectGraphs":true,"m_FxEnabled":true},"in2DMode":false,"pivot":{"x":3.3902313709259035,"y":1.383360505104065,"z":-1.5135036706924439},"rotation":{"x":-0.1343880146741867,"y":0.5293614268302918,"z":-0.0841444730758667,"w":-0.8328270316123962},"size":1.15345299243927,"orthographic":false}